better_test_preview/__init__.py
better_test_preview/better_test_preview/__init__.py
better_test_preview/better_test_preview/main.py
better_test_preview/better_test_preview/templates/index.html
better_test_preview-0.1.1.data/data/templates/index.html
better_test_preview-0.1.1.dist-info/LICENSE
better_test_preview-0.1.1.dist-info/METADATA
better_test_preview-0.1.1.dist-info/WHEEL
better_test_preview-0.1.1.dist-info/top_level.txt
better_test_preview-0.1.1.dist-info/RECORD
