Metadata-Version: 2.1
Name: better-test-preview
Version: 0.1.1
Summary: FastAPI app
Author: HangoverHGV
License-File: LICENSE
Requires-Dist: fastapi
Requires-Dist: uvicorn
Requires-Dist: jinja2
Requires-Dist: pydantic
Requires-Dist: pytest
Requires-Dist: pytest-html
Requires-Dist: ansi2html
